gradebook_tray/__init__.py
gradebook_tray/__main__.py
gradebook_tray/assets/error.png
gradebook_tray/assets/fetch.png
gradebook_tray/assets/icon.png
gradebook_tray/assets/update.png
gradebook_tray/utils/__init__.py
gradebook_tray/utils/calc.py
gradebook_tray/utils/config.py
gradebook_tray/utils/db.py
gradebook_tray/utils/log.py
gradebook_tray/utils/studentvue.py
gradebook_tray/utils/util.py
gradebook_tray-0.1.2.dist-info/METADATA
gradebook_tray-0.1.2.dist-info/WHEEL
gradebook_tray-0.1.2.dist-info/RECORD
