Metadata-Version: 2.1
Name: gradebook_tray
Version: 0.1.2
Summary: A tray to track your StudentVUE grade
License: MIT
Author: Yubo Cao
Author-email: cao2006721@gmail.com
Requires-Python: >=3.11,<4.0
Classifier: License :: OSI Approved :: MIT License
Classifier: Programming Language :: Python :: 3
Classifier: Programming Language :: Python :: 3.11
Classifier: Programming Language :: Python :: 3.12
Requires-Dist: pillow (>=10.4.0,<11.0.0)
Requires-Dist: psgtray (>=5.0.0,<6.0.0)
Requires-Dist: pysimplegui (>=5.0.6,<6.0.0)
Requires-Dist: pyyaml (>=6.0.2,<7.0.0)
Requires-Dist: rich (>=13.7.1,<14.0.0)
Requires-Dist: zeep (>=4.2.1,<5.0.0)
